COPYING
MANIFEST.in
README.md
ligo-lvalert.spec
setup.cfg
setup.py
bin/lvalert_admin
bin/lvalert_listen
bin/lvalert_send
debian/README.Debian
debian/changelog
debian/compat
debian/control
debian/copyright
debian/rules
debian/source/format
ligo/__init__.py
ligo/lvalert/__init__.py
ligo/lvalert/certs.pem
ligo/lvalert/lvstanzaprocessor.py
ligo/lvalert/pubsub.py
ligo/lvalert/tool.py
ligo/lvalert/utils.py
ligo/lvalert/version.py
ligo_lvalert.egg-info/PKG-INFO
ligo_lvalert.egg-info/SOURCES.txt
ligo_lvalert.egg-info/dependency_links.txt
ligo_lvalert.egg-info/entry_points.txt
ligo_lvalert.egg-info/namespace_packages.txt
ligo_lvalert.egg-info/requires.txt
ligo_lvalert.egg-info/top_level.txt