Metadata-Version: 1.2
Name: ligo-lvalert
Version: 1.5.4
Summary: LIGO-Virgo Alert Network
Home-page: https://wiki.ligo.org/DASWG/LVAlert
Author: Tanner Prestegard, Alexander Pace, Leo Singer
Author-email: tanner.prestegard@ligo.org, alexander.pace@ligo.org, leo.singer@ligo.org
License: GPLv2+
Platform: UNKNOWN
Classifier: Development Status :: 3 - Alpha
Classifier: Environment :: Console
Classifier: Intended Audience :: Science/Research
Classifier: License :: OSI Approved :: GNU General Public License v2 or later (GPLv2+)
Classifier: Operating System :: POSIX
Classifier: Programming Language :: Python :: 2
Classifier: Programming Language :: Python :: 2.7
Classifier: Programming Language :: Python :: 3
Classifier: Programming Language :: Python :: 3.5
Classifier: Programming Language :: Python :: 3.6
Classifier: Programming Language :: Python :: 3.7
Classifier: Topic :: Internet
Classifier: Topic :: Scientific/Engineering :: Astronomy
Classifier: Topic :: Scientific/Engineering :: Physics
Requires-Python: >=2.7
